AUTHORS.rst
CONTRIBUTING.rst
HISTORY.rst
LICENSE.txt
MANIFEST.in
README.rst
setup.cfg
setup.py
versioneer.py
docs/Makefile
docs/api.rst
docs/authors.rst
docs/conf.py
docs/contributing.rst
docs/history.rst
docs/index.rst
docs/installation.rst
docs/make.bat
docs/readme.rst
docs/usage.rst
kenjutsu/__init__.py
kenjutsu/_version.py
kenjutsu/blocks.py
kenjutsu/core.py
kenjutsu/format.py
kenjutsu/kenjutsu.py
kenjutsu/measure.py
kenjutsu/operators.py
kenjutsu.egg-info/PKG-INFO
kenjutsu.egg-info/SOURCES.txt
kenjutsu.egg-info/dependency_links.txt
kenjutsu.egg-info/not-zip-safe
kenjutsu.egg-info/top_level.txt
tests/__init__.py
tests/test_blocks.py
tests/test_core.py
tests/test_format.py
tests/test_kenjutsu.py
tests/test_measure.py
tests/test_operators.py